[
  {
    "titulo": "Rolex presenta el nuevo Submariner 2025",
    "fecha": "2025-07-15",
    "link": "https://www.rolex.com/es/watches/submariner.html",
    "resumen": "La icónica línea de buceo se renueva con un calibre mejorado y ligeros cambios estéticos que mantienen su ADN clásico."
  },
  {
    "titulo": "Omega Speedmaster gana el premio al mejor cronógrafo",
    "fecha": "2025-06-28",
    "link": "https://www.omegawatches.com/es-es/watch-omega-speedmaster",
    "resumen": "El Speedmaster Professional Moonwatch recibe el galardón en la feria internacional de relojería de Ginebra."
  },
  {
    "titulo": "Audemars Piguet lanza Royal Oak de titanio",
    "fecha": "2025-05-10",
    "link": "https://www.audemarspiguet.com/com/es/home.html",
    "resumen": "La manufactura suiza introduce una versión ultraligera de su modelo más emblemático, limitada a solo 250 piezas."
  }
]
